{
  "id": [
    "33650832"
  ],
  "source": [
    "MED"
  ],
  "pmid": [
    "33650832"
  ],
  "pmcid": [
    "PMC7944126"
  ],
  "fullTextIdList": [
    {
      "fullTextId": [
        "PMC7944126"
      ]
    }
  ],
  "doi": [
    "10.22074/cellj.2021.7931"
  ],
  "title": [
    "Stem Cells from Human Exfoliated Deciduous Tooth Exhibit Stromal-Derived Inducing Activity and Lead to Generation of Neural Crest Cells from Human Embryonic Stem Cells."
  ],
  "authorString": [
    "Karbalaie KH, Tanhaei S, Rabiei F, Kiani-Esfahani A, Masoudi NS, Nasr-Esfahani MH, Baharvand H."
  ],
  "authorList": [
    {
      "author": [
        {
          "fullName": [
            "Karbalaie KH"
          ],
          "firstName": [
            "K Hadijeh"
          ],
          "lastName": [
            "Karbalaie"
          ],
          "initials": [
            "KH"
          ],
          "authorAffiliationDetailsList": [
            {
              "authorAffiliation": [
                {
                  "affiliation": [
                    "Department of Cellular Biotechnology at Cell Science Research Center, Royan Institute for Biotechnology, ACECR, Isfahan, Iran."
                  ]
                }
              ]
            }
          ]
        },
        {
          "fullName": [
            "Tanhaei S"
          ],
          "firstName": [
            "Somayyeh"
          ],
          "lastName": [
            "Tanhaei"
          ],
          "initials": [
            "S"
          ],
          "authorAffiliationDetailsList": [
            {
              "authorAffiliation": [
                {
                  "affiliation": [
                    "Department of Molecular Biotechnology at Cell Science Research Center, Royan Institute for Biotechnology, ACECR, Isfahan, Iran."
                  ]
                }
              ]
            }
          ]
        },
        {
          "fullName": [
            "Rabiei F"
          ],
          "firstName": [
            "Farzaneh"
          ],
          "lastName": [
            "Rabiei"
          ],
          "initials": [
            "F"
          ],
          "authorAffiliationDetailsList": [
            {
              "authorAffiliation": [
                {
                  "affiliation": [
                    "Department of Molecular Biotechnology at Cell Science Research Center, Royan Institute for Biotechnology, ACECR, Isfahan, Iran."
                  ]
                }
              ]
            }
          ]
        },
        {
          "fullName": [
            "Kiani-Esfahani A"
          ],
          "firstName": [
            "Abbas"
          ],
          "lastName": [
            "Kiani-Esfahani"
          ],
          "initials": [
            "A"
          ],
          "authorAffiliationDetailsList": [
            {
              "authorAffiliation": [
                {
                  "affiliation": [
                    "Department of Molecular Biotechnology at Cell Science Research Center, Royan Institute for Biotechnology, ACECR, Isfahan, Iran."
                  ]
                }
              ]
            }
          ]
        },
        {
          "fullName": [
            "Masoudi NS"
          ],
          "firstName": [
            "Najmeh Sadat"
          ],
          "lastName": [
            "Masoudi"
          ],
          "initials": [
            "NS"
          ],
          "authorAffiliationDetailsList": [
            {
              "authorAffiliation": [
                {
                  "affiliation": [
                    "Department of Genetics at Reproductive Biomedicine Research Center, Royan Institute for Reproductive Biomedicine, ACECR, Tehran, Iran."
                  ]
                }
              ]
            }
          ]
        },
        {
          "fullName": [
            "Nasr-Esfahani MH"
          ],
          "firstName": [
            "Mohammad Hossein"
          ],
          "lastName": [
            "Nasr-Esfahani"
          ],
          "initials": [
            "MH"
          ],
          "authorAffiliationDetailsList": [
            {
              "authorAffiliation": [
                {
                  "affiliation": [
                    "Department of Cellular Biotechnology at Cell Science Research Center, Royan Institute for Biotechnology, ACECR, Isfahan, Iran.Email: mh.nasr-esfahani@RoyanInstitute.org."
                  ]
                }
              ]
            }
          ]
        },
        {
          "fullName": [
            "Baharvand H"
          ],
          "firstName": [
            "Hossein"
          ],
          "lastName": [
            "Baharvand"
          ],
          "initials": [
            "H"
          ],
          "authorAffiliationDetailsList": [
            {
              "authorAffiliation": [
                {
                  "affiliation": [
                    "Department of Stem Cells and Developmental Biology at Cell Science Research Center, Royan Institute for Stem Cell Biology and Technology, ACECR, Tehran, Iran."
                  ]
                },
                {
                  "affiliation": [
                    "Department of Developmental Biology, University of Science and Culture, ACECR, Tehran, Iran."
                  ]
                }
              ]
            }
          ]
        }
      ]
    }
  ],
  "journalInfo": [
    {
      "issue": [
        "1"
      ],
      "volume": [
        "23"
      ],
      "journalIssueId": [
        "3122529"
      ],
      "dateOfPublication": [
        "2021 Apr"
      ],
      "monthOfPublication": [
        "4"
      ],
      "yearOfPublication": [
        "2021"
      ],
      "printPublicationDate": [
        "2021-04-01"
      ],
      "journal": [
        {
          "title": [
            "Cell journal"
          ],
          "ISOAbbreviation": [
            "Cell J"
          ],
          "medlineAbbreviation": [
            "Cell J"
          ],
          "NLMid": [
            "101566618"
          ],
          "ISSN": [
            "2228-5806"
          ],
          "ESSN": [
            "2228-5814"
          ]
        }
      ]
    }
  ],
  "pubYear": [
    "2021"
  ],
  "pageInfo": [
    "140-142"
  ],
  "abstractText": [
    "In this article which was published in Cell J, Vol 17, No 1, Spring 2015, on pages 37-48, we found that Figure 1H, Figure 2 (OTX2, row 3), and Figure 3 (row 4) had been published incorrectly. The following figures are corrected. The authors would like to apologies for any inconvenience caused."
  ],
  "affiliation": [
    "Department of Cellular Biotechnology at Cell Science Research Center, Royan Institute for Biotechnology, ACECR, Isfahan, Iran."
  ],
  "publicationStatus": [
    "ppublish"
  ],
  "language": [
    "eng"
  ],
  "pubModel": [
    "Print-Electronic"
  ],
  "pubTypeList": [
    {
      "pubType": [
        "Published Erratum",
        "correction"
      ]
    }
  ],
  "keywordList": [
    {
      "keyword": [
        "Differentiation",
        "Human embryonic stem cells",
        "Sdia",
        "Neural Crest Cells",
        "Shed"
      ]
    }
  ],
  "fullTextUrlList": [
    {
      "fullTextUrl": [
        {
          "availability": [
            "Subscription required"
          ],
          "availabilityCode": [
            "S"
          ],
          "documentStyle": [
            "doi"
          ],
          "site": [
            "DOI"
          ],
          "url": [
            "https://doi.org/10.22074/cellj.2021.7931"
          ]
        },
        {
          "availability": [
            "Open access"
          ],
          "availabilityCode": [
            "OA"
          ],
          "documentStyle": [
            "html"
          ],
          "site": [
            "Europe_PMC"
          ],
          "url": [
            "https://europepmc.org/articles/PMC7944126"
          ]
        },
        {
          "availability": [
            "Open access"
          ],
          "availabilityCode": [
            "OA"
          ],
          "documentStyle": [
            "pdf"
          ],
          "site": [
            "Europe_PMC"
          ],
          "url": [
            "https://europepmc.org/articles/PMC7944126?pdf=render"
          ]
        }
      ]
    }
  ],
  "commentCorrectionList": [
    {
      "commentCorrection": [
        {
          "id": [
            "25870833"
          ],
          "source": [
            "MED"
          ],
          "reference": [
            "Cell J. 2015 Spring;17(1):37-48"
          ],
          "type": [
            "Erratum for"
          ],
          "orderIn": [
            "1"
          ]
        }
      ]
    }
  ],
  "isOpenAccess": [
    "Y"
  ],
  "inEPMC": [
    "Y"
  ],
  "inPMC": [
    "N"
  ],
  "hasPDF": [
    "Y"
  ],
  "hasBook": [
    "N"
  ],
  "hasSuppl": [
    "N"
  ],
  "citedByCount": [
    "0"
  ],
  "hasData": [
    "N"
  ],
  "hasReferences": [
    "N"
  ],
  "hasTextMinedTerms": [
    "Y"
  ],
  "hasDbCrossReferences": [
    "N"
  ],
  "hasLabsLinks": [
    "N"
  ],
  "license": [
    "cc by"
  ],
  "authMan": [
    "N"
  ],
  "epmcAuthMan": [
    "N"
  ],
  "nihAuthMan": [
    "N"
  ],
  "hasTMAccessionNumbers": [
    "N"
  ],
  "dateOfCreation": [
    "2021-03-02"
  ],
  "firstIndexDate": [
    "2021-03-03"
  ],
  "fullTextReceivedDate": [
    "2021-03-17"
  ],
  "dateOfRevision": [
    "2021-03-16"
  ],
  "electronicPublicationDate": [
    "2021-03-01"
  ],
  "firstPublicationDate": [
    "2021-03-01"
  ]
}